h5darkframes/__init__.py
h5darkframes/asi_zwo.py
h5darkframes/camera.py
h5darkframes/control_range.py
h5darkframes/create_library.py
h5darkframes/dummy_camera.py
h5darkframes/duration_estimate.py
h5darkframes/executables.py
h5darkframes/fuse_libraries.py
h5darkframes/get_image.py
h5darkframes/h5.py
h5darkframes/h5types.py
h5darkframes/image_library.py
h5darkframes/image_stats.py
h5darkframes/main.py
h5darkframes/neighbors.py
h5darkframes/progress.py
h5darkframes/py.typed
h5darkframes/substract.py
h5darkframes/toml_config.py
h5darkframes/validation.py
h5darkframes-0.1.7.dist-info/METADATA
h5darkframes-0.1.7.dist-info/WHEEL
h5darkframes-0.1.7.dist-info/entry_points.txt
h5darkframes-0.1.7.dist-info/licenses/LICENSE
h5darkframes-0.1.7.dist-info/RECORD
