Metadata-Version: 2.4
Name: h5darkframes
Version: 0.1.7
Summary: python API for creating and using hdf5 darkframes libraries 
License: BSD-3-Clause
License-File: LICENSE
Author: Vincent Berenz
Author-email: vberenz@tuebingen.mpg.de
Requires-Python: >=3.12,<4
Classifier: License :: OSI Approved :: BSD License
Classifier: Programming Language :: Python :: 3
Classifier: Programming Language :: Python :: 3.12
Classifier: Programming Language :: Python :: 3.13
Classifier: Programming Language :: Python :: 3.14
Requires-Dist: alive-progress (>=3.3.0,<4.0.0)
Requires-Dist: astropy (>=7.2.0,<8.0.0)
Requires-Dist: auto-stretch (>=0.0.3,<0.0.4)
Requires-Dist: h5py (>=3.15.1,<4.0.0)
Requires-Dist: opencv-python (>=4.12.0.88,<5.0.0.0)
Requires-Dist: pytest (>=9.0.1,<10.0.0)
Requires-Dist: rich (>=14.2.0,<15.0.0)
Requires-Dist: toml (>=0.10.2,<0.11.0)
Project-URL: Homepage, https://github.com/MPI-IS/h5darkframes
Project-URL: Repository, https://github.com/MPI-IS/h5darkframes
